MANIFEST.in
hgvers.py
setup.py
urllib2_kerberos.py
urllib2_kerberos.egg-info/PKG-INFO
urllib2_kerberos.egg-info/SOURCES.txt
urllib2_kerberos.egg-info/dependency_links.txt
urllib2_kerberos.egg-info/top_level.txt